pyppl_jobtime.py
pyppl_jobtime-0.0.4.dist-info/entry_points.txt
pyppl_jobtime-0.0.4.dist-info/LICENSE
pyppl_jobtime-0.0.4.dist-info/WHEEL
pyppl_jobtime-0.0.4.dist-info/METADATA
pyppl_jobtime-0.0.4.dist-info/RECORD
